filecopy_installer/__init__.py
filecopy_installer/filecopy_installer.py
certbot_filecopy_installer-1.0.0.dist-info/LICENSE
certbot_filecopy_installer-1.0.0.dist-info/METADATA
certbot_filecopy_installer-1.0.0.dist-info/WHEEL
certbot_filecopy_installer-1.0.0.dist-info/entry_points.txt
certbot_filecopy_installer-1.0.0.dist-info/top_level.txt
certbot_filecopy_installer-1.0.0.dist-info/RECORD
