Metadata-Version: 2.1
Name: certbot-filecopy-installer
Version: 1.0.0
Summary: Simple file copy installer for certbot
Home-page: https://github.com/NotBobTheBuilder/certbot-filecopy-installer
Maintainer: Jack Wearden
Maintainer-email: jack@jackwearden.co.uk
License: MIT License
Keywords: letsencrypt certbot installer
Requires-Python: >=3.6
License-File: LICENSE
Requires-Dist: acme
Requires-Dist: certbot
Requires-Dist: setuptools
Provides-Extra: test
Requires-Dist: pytest ; extra == 'test'
